{
    "packages": {
        "wdframe": {
            "5.0.2": {
                "name": "wdframe5.0.2",
                "version": "5.0.2",
                "source": {
                    "url": "/servidor/http/wdframe5/public_html/wdframe5.0.2/",
                    "type": "git",
                    "reference": "master"
                }
            },
            "5.0.1": {
                "name": "wdframe5.0.1",
                "version": "5.0.1",
                "source": {
                    "url": "/servidor/http/wdframe5/public_html/wdframe5.0.1/",
                    "type": "git",
                    "reference": "master"
                }
            },
            "4.3.1": {
                "name": "wdframe4.3.1",
                "version": "4.3.1",
                "source": {
                    "url": "/servidor/http/wdframe5/public_html/wdframe4.3.1/",
                    "type": "git",
                    "reference": "master"
                }
            }
        }
    }
}